yollama/__init__.py
yollama/lib.py
yollama-2.1.0.dist-info/LICENSE
yollama-2.1.0.dist-info/METADATA
yollama-2.1.0.dist-info/WHEEL
yollama-2.1.0.dist-info/top_level.txt
yollama-2.1.0.dist-info/RECORD
