Metadata-Version: 2.2
Name: yollama
Version: 2.1.0
Summary: helper functions for Ollama with Langchain
Home-page: https://github.com/markets-agent/yollama
Author: yactouat
Author-email: yactouat@yactouat.com
License: MIT
License-File: LICENSE
Requires-Dist: langchain-core
Requires-Dist: langchain-ollama
Dynamic: author
Dynamic: author-email
Dynamic: description
Dynamic: description-content-type
Dynamic: home-page
Dynamic: license
Dynamic: requires-dist
Dynamic: summary
